create_sqlalchemy_app/__init__.py
create_sqlalchemy_app/cli.py
create_sqlalchemy_app/config.py
create_sqlalchemy_app/generator.py
create_sqlalchemy_app/starters/__init__.py
create_sqlalchemy_app/starters/auth/__init__.py
create_sqlalchemy_app/starters/auth/models/__init__.py.jinja2
create_sqlalchemy_app/starters/auth/models/user.py.jinja2
create_sqlalchemy_app/starters/auth/tests/test_user.py.jinja2
create_sqlalchemy_app/starters/blog/__init__.py
create_sqlalchemy_app/starters/blog/models/__init__.py.jinja2
create_sqlalchemy_app/starters/blog/models/comment.py.jinja2
create_sqlalchemy_app/starters/blog/models/post.py.jinja2
create_sqlalchemy_app/starters/blog/models/tag.py.jinja2
create_sqlalchemy_app/starters/blog/models/user.py.jinja2
create_sqlalchemy_app/starters/blog/tests/test_blog.py.jinja2
create_sqlalchemy_app/starters/ecommerce/models/__init__.py.jinja2
create_sqlalchemy_app/starters/ecommerce/models/category.py.jinja2
create_sqlalchemy_app/starters/ecommerce/models/order.py.jinja2
create_sqlalchemy_app/starters/ecommerce/models/product.py.jinja2
create_sqlalchemy_app/starters/ecommerce/models/user.py.jinja2
create_sqlalchemy_app/starters/ecommerce/tests/test_ecommerce.py.jinja2
create_sqlalchemy_app/templates/core/README.md.jinja2
create_sqlalchemy_app/templates/core/docker-compose.yml.jinja2
create_sqlalchemy_app/templates/core/env.jinja2
create_sqlalchemy_app/templates/core/gitignore.jinja2
create_sqlalchemy_app/templates/database/db.py.jinja2
create_sqlalchemy_app/templates/docs/CSV_IMPORT.md.jinja2
create_sqlalchemy_app/templates/frameworks/fastapi/health.py.jinja2
create_sqlalchemy_app/templates/frameworks/fastapi/main.py.jinja2
create_sqlalchemy_app/templates/frameworks/flask/app_init.py.jinja2
create_sqlalchemy_app/templates/frameworks/flask/health.py.jinja2
create_sqlalchemy_app/templates/frameworks/flask/index.html.jinja2
create_sqlalchemy_app/templates/frameworks/flask/run.py.jinja2
create_sqlalchemy_app-1.0.2.dist-info/METADATA
create_sqlalchemy_app-1.0.2.dist-info/WHEEL
create_sqlalchemy_app-1.0.2.dist-info/entry_points.txt
create_sqlalchemy_app-1.0.2.dist-info/licenses/LICENSE
create_sqlalchemy_app-1.0.2.dist-info/RECORD
