Metadata-Version: 2.4
Name: create-sqlalchemy-app
Version: 1.0.2
Summary: Create SQLAlchemy applications with a single command - like Create React App for Python backends
Project-URL: Homepage, https://github.com/ShawnaRStaff/create-sqlalchemy-app
Project-URL: Documentation, https://github.com/ShawnaRStaff/create-sqlalchemy-app#readme
Project-URL: Repository, https://github.com/ShawnaRStaff/create-sqlalchemy-app
Project-URL: Issues, https://github.com/ShawnaRStaff/create-sqlalchemy-app/issues
Author-email: "Shawna R. Staff" <shawnastaff@gmail.com>
License-Expression: MIT
License-File: LICENSE
Keywords: alembic,cli,database,fastapi,flask,mysql,orm,postgresql,project-generator,scaffolding,sqlalchemy,sqlite
Classifier: Development Status :: 4 - Beta
Classifier: Environment :: Console
Classifier: Framework :: FastAPI
Classifier: Framework :: Flask
Classifier: Intended Audience :: Developers
Classifier: License :: OSI Approved :: MIT License
Classifier: Operating System :: OS Independent
Classifier: Programming Language :: Python :: 3
Classifier: Programming Language :: Python :: 3.10
Classifier: Programming Language :: Python :: 3.11
Classifier: Programming Language :: Python :: 3.12
Classifier: Topic :: Database
Classifier: Topic :: Software Development :: Code Generators
Requires-Python: >=3.10
Requires-Dist: click>=8.0.0
Requires-Dist: jinja2>=3.0.0
Requires-Dist: rich>=13.0.0
Provides-Extra: dev
Requires-Dist: black>=23.0.0; extra == 'dev'
Requires-Dist: pytest-cov>=4.0.0; extra == 'dev'
Requires-Dist: pytest>=7.0.0; extra == 'dev'
Requires-Dist: ruff>=0.1.0; extra == 'dev'
